nailguard/alerts/__init__.py
nailguard/alerts/base.py
nailguard/alerts/beep.py
nailguard/alerts/notification.py
nailguard/alerts/screen.py
nailguard/assets/error.wav
nailguard/assets/stop.png
nailguard/detectors/__init__.py
nailguard/detectors/base.py
nailguard/detectors/mediapipe.py
nailguard/main.py
nailguard/nailguard.py
nailguard-0.3.1.dist-info/METADATA
nailguard-0.3.1.dist-info/WHEEL
nailguard-0.3.1.dist-info/entry_points.txt
nailguard-0.3.1.dist-info/RECORD
