Metadata-Version: 2.1
Name: nailguard
Version: 0.3.1
Summary: Making sure you don't bite your nails
Author: klima7
Author-email: github@mail.ukasz.com
Requires-Python: >=3.10,<4.0
Classifier: Programming Language :: Python :: 3
Classifier: Programming Language :: Python :: 3.10
Classifier: Programming Language :: Python :: 3.11
Classifier: Programming Language :: Python :: 3.12
Classifier: Programming Language :: Python :: 3.13
Requires-Dist: click (>=8.1.7,<9.0.0)
Requires-Dist: mediapipe (>=0.10.18,<0.11.0)
Requires-Dist: notify-py (>=0.3.43,<0.4.0)
Requires-Dist: numpy (<2)
Requires-Dist: opencv-python (>=4.10.0.84,<5.0.0.0)
Requires-Dist: pillow (>=11.0.0,<12.0.0)
Requires-Dist: pygame (>=2.6.1,<3.0.0)
Requires-Dist: screeninfo (>=0.8.1,<0.9.0)
